pylliterate/__init__.py
pylliterate/__main__.py
pylliterate/cli.py
pylliterate/config.py
pylliterate/core.py
pylliterate-0.0.6.dist-info/entry_points.txt
pylliterate-0.0.6.dist-info/LICENSE
pylliterate-0.0.6.dist-info/METADATA
pylliterate-0.0.6.dist-info/WHEEL
pylliterate-0.0.6.dist-info/RECORD
