Metadata-Version: 2.1
Name: pylliterate
Version: 0.0.6
Summary: Unobtrusive literate programming experience for Python pragmatists
License: MIT
Author: Alejandro Piad
Author-email: alepiad@gmail.com
Requires-Python: >=3.12,<4.0
Classifier: License :: OSI Approved :: MIT License
Classifier: Programming Language :: Python :: 3
Classifier: Programming Language :: Python :: 3.12
Requires-Dist: PyYAML (>=6.0.1,<7.0.0)
Requires-Dist: pydantic (>=2.7.1,<3.0.0)
Requires-Dist: rich (>=13.7.1,<14.0.0)
Requires-Dist: typer (>=0.12.3,<0.13.0)
Requires-Dist: watchdog (>=2.3.1,<3.0.0)
